{   
    "id": 9,
    "name": "Bracelet Algérie Doré",
    "description": "Couleur du métal: Or, Métal: Acier Inoxydable, Condition: 100% nouveau, Emballage: Sachet en organza, Fermoir: Fermoir mousqueton, Maille: Maille forçat, Couleur: Or, Traitement de surface: Poli et satiné, Taille: 18.5 cm longueur / 1.6 cm largeur / 0.2 cm épaisseur, Poids: 6 grammes, Redimensionnable: Non.",
    "unitPrice": 12.9,
    "path_img1": "/public/img/R1153.001.png",
    "path_img2": "/public/img/R1153.003.jpg",
    "path_img3": null,
    "path_img4": null,
    "ref": "R1153"
}